[
  {
    "id": "C9-010",
    "category": "chapter-9-tables",
    "necArticle": "Chapter 9",
    "difficulty": "master",
    "questionText": "A feeder is installed in Electrical Metallic Tubing (EMT) and consists of three 1/0 AWG THHN conductors and one 6 AWG THHN equipment grounding conductor. What is the minimum trade size EMT required for this installation?",
    "options": [
      "1",
      "1 1/4",
      "1 1/2",
      "2"
    ],
    "correctAnswer": 2,
    "explanation": "Chapter 9 Note 3 requires EGCs to be included in fill calculations. Using Table 5: 1/0 THHN = 0.1855 in² and 6 AWG THHN = 0.0507 in². Total area = (3 × 0.1855) + 0.0507 = 0.6072 in². Table 1 allows 40% fill for over 2 wires. In Table 4 for EMT, 1 1/4-inch allows 0.598 in² (too small). You must step up to 1 1/2-inch, which allows 0.814 in².",
    "necReference": "Chapter 9, Tables 1, 4, and 5",
    "sparkyTip": "Don't forget the EGC! If you omit the ground wire in this calculation, the area is 0.5565 in², which perfectly traps you into choosing 1 1/4-inch EMT."
  },
  {
    "id": "C9-014",
    "category": "chapter-9-tables",
    "necArticle": "Chapter 9",
    "difficulty": "master",
    "questionText": "What is the DC resistance per 1000 feet of uncoated #12 AWG copper conductor at 75°C?",
    "options": [
      "1.21 ohms",
      "1.93 ohms",
      "3.07 ohms",
      "4.89 ohms"
    ],
    "correctAnswer": 1,
    "explanation": "According to Chapter 9 Table 8, #12 AWG uncoated copper has a DC resistance of 1.93 ohms per 1000 feet at 75°C.",
    "necReference": "Chapter 9, Table 8",
    "sparkyTip": "#12 copper ≈ 2 ohms per 1000 ft. Use Table 8 for DC voltage drop calculations!"
  },
  {
    "id": "C9-036",
    "category": "chapter-9-tables",
    "necArticle": "Chapter 9",
    "difficulty": "master",
    "questionText": "What is the stranding for a #12 AWG stranded copper conductor?",
    "options": [
      "Solid only",
      "7 strands",
      "19 strands",
      "37 strands"
    ],
    "correctAnswer": 1,
    "explanation": "According to Chapter 9 Table 8, #12 AWG stranded conductor typically has 7 strands (sometimes 19 for fine stranding).",
    "necReference": "Chapter 9, Table 8",
    "sparkyTip": "#12 stranded = 7 strands. Larger conductors use more strands for flexibility."
  },
  {
    "id": "C9-041",
    "category": "chapter-9-tables",
    "necArticle": "Chapter 9",
    "difficulty": "master",
    "questionText": "What is the area in circular mils of a 4/0 AWG conductor?",
    "options": [
      "83,690 cmil",
      "105,500 cmil",
      "133,100 cmil",
      "211,600 cmil"
    ],
    "correctAnswer": 3,
    "explanation": "According to Chapter 9 Table 8, a 4/0 AWG conductor has an area of 211,600 circular mils.",
    "necReference": "Chapter 9, Table 8",
    "sparkyTip": "4/0 AWG ≈ 212 kcmil. The next size up is 250 kcmil."
  },
  {
    "id": "C9-046",
    "category": "chapter-9-tables",
    "necArticle": "Chapter 9",
    "difficulty": "master",
    "questionText": "What is the AC resistance of #12 AWG copper in steel conduit per 1000 feet?",
    "options": [
      "1.7 ohms",
      "2.0 ohms",
      "2.4 ohms",
      "3.2 ohms"
    ],
    "correctAnswer": 1,
    "explanation": "According to Chapter 9 Table 9, #12 AWG copper in steel conduit has an AC resistance of approximately 2.0 ohms per 1000 feet at 75°C.",
    "necReference": "Chapter 9, Table 9",
    "sparkyTip": "AC resistance in steel conduit is higher than DC due to skin effect and conduit losses."
  },
  {
    "id": "C9-054",
    "category": "chapter-9-tables",
    "necArticle": "Chapter 9",
    "difficulty": "master",
    "questionText": "What is the approximate area of a 500 kcmil THHN conductor?",
    "options": [
      "0.5917 sq in",
      "0.7073 sq in",
      "0.8316 sq in",
      "0.9676 sq in"
    ],
    "correctAnswer": 1,
    "explanation": "According to Chapter 9 Table 5, a 500 kcmil THHN conductor has an approximate area of 0.7073 square inches.",
    "necReference": "Chapter 9, Table 5",
    "sparkyTip": "500 kcmil THHN ≈ 0.7 sq in. Large conductors require careful conduit sizing!"
  },
  {
    "id": "C9-056",
    "category": "chapter-9-tables",
    "necArticle": "Chapter 9",
    "difficulty": "master",
    "questionText": "What is the DC resistance per 1000 feet of #4 AWG copper at 75°C?",
    "options": [
      "0.194 ohms",
      "0.308 ohms",
      "0.491 ohms",
      "0.764 ohms"
    ],
    "correctAnswer": 1,
    "explanation": "According to Chapter 9 Table 8, #4 AWG uncoated copper has a DC resistance of approximately 0.308 ohms per 1000 feet at 75°C.",
    "necReference": "Chapter 9, Table 8",
    "sparkyTip": "#4 copper ≈ 0.3 ohms per 1000 ft. Roughly 1/6 the resistance of #12!"
  },
  {
    "id": "C9-058",
    "category": "chapter-9-tables",
    "necArticle": "Chapter 9",
    "difficulty": "master",
    "questionText": "What is the reactance (XL) per 1000 feet for conductors in steel conduit?",
    "options": [
      "It varies by conductor size",
      "It is constant at approximately 0.050 ohms",
      "It is constant at approximately 0.068 ohms",
      "It is zero for all conductors"
    ],
    "correctAnswer": 0,
    "explanation": "Reactance varies by conductor size and conduit type. In steel conduit, it ranges from about 0.050 to 0.068 ohms per 1000 feet depending on conductor size.",
    "necReference": "Chapter 9, Table 9",
    "sparkyTip": "Reactance varies with conductor size. Larger conductors generally have lower reactance."
  }
]
